autoreporter/__init__.py
autoreporter/builder.py
autoreporter-0.0.2.dist-info/LICENSE
autoreporter-0.0.2.dist-info/METADATA
autoreporter-0.0.2.dist-info/WHEEL
autoreporter-0.0.2.dist-info/top_level.txt
autoreporter-0.0.2.dist-info/RECORD
