Metadata-Version: 2.1
Name: autoreporter
Version: 0.0.2
Summary: To easily format, design, and automatically generate reports
Home-page: https://github.com/davidzqhuang/autoreporter
Author: David Huang
Author-email: dhuang26@gmail.com
License: UNKNOWN
Platform: UNKNOWN
Classifier: Programming Language :: Python :: 3
Classifier: License :: OSI Approved :: MIT License
Classifier: Operating System :: OS Independent
Requires-Python: >=3.6
License-File: LICENSE
